leaddbsinterface/__init__.py
leaddbsinterface/allocate_axons.py
leaddbsinterface/convert_input_dictionary.py
leaddbsinterface/default_settings.py
leaddbsinterface/lead_settings.py
ossdbs/__init__.py
ossdbs/_version.py
ossdbs/api.py
ossdbs/main.py
ossdbs/axon_processing/README.md
ossdbs/axon_processing/__init__.py
ossdbs/axon_processing/axon_default_MRG2002.py
ossdbs/axon_processing/axon_models.py
ossdbs/axon_processing/main.py
ossdbs/axon_processing/neuron_model.py
ossdbs/axon_processing/utilities.py
ossdbs/axon_processing/neuron_templates/MRG2002/axnode.mod
ossdbs/axon_processing/neuron_templates/MRG2002/axon4pyfull.hoc
ossdbs/axon_processing/neuron_templates/MRG2002/readme_McIntyre2002.txt
ossdbs/axon_processing/neuron_templates/McNeal1976/README.md
ossdbs/axon_processing/neuron_templates/McNeal1976/axon10.hoc
ossdbs/axon_processing/neuron_templates/McNeal1976/axon5.hoc
ossdbs/axon_processing/neuron_templates/McNeal1976/basicrig.ses
ossdbs/axon_processing/neuron_templates/McNeal1976/fh.mod
ossdbs/axon_processing/neuron_templates/McNeal1976/fsquare.mod
ossdbs/axon_processing/neuron_templates/McNeal1976/fzap.mod
ossdbs/axon_processing/neuron_templates/McNeal1976/initA.hoc
ossdbs/axon_processing/neuron_templates/McNeal1976/initB10.hoc
ossdbs/axon_processing/neuron_templates/McNeal1976/initB5.hoc
ossdbs/axon_processing/neuron_templates/McNeal1976/init_B10_extracellular.hoc
ossdbs/axon_processing/neuron_templates/McNeal1976/init_B5_extracellular.hoc
ossdbs/axon_processing/neuron_templates/McNeal1976/interpxyz.hoc
ossdbs/axon_processing/neuron_templates/McNeal1976/mosinit.hoc
ossdbs/axon_processing/neuron_templates/McNeal1976/protocolsA.hoc
ossdbs/axon_processing/neuron_templates/McNeal1976/protocolsB.hoc
ossdbs/axon_processing/neuron_templates/McNeal1976/readme.html
ossdbs/axon_processing/neuron_templates/McNeal1976/thresh4.hoc
ossdbs/axon_processing/neuron_templates/McNeal1976/varstep.ses
ossdbs/axon_processing/neuron_templates/McNeal1976/vext_eext.ses
ossdbs-0.5.3.dist-info/licenses/LICENSE
ossdbs-0.5.3.dist-info/METADATA
ossdbs-0.5.3.dist-info/WHEEL
ossdbs-0.5.3.dist-info/entry_points.txt
ossdbs-0.5.3.dist-info/top_level.txt
ossdbs-0.5.3.dist-info/RECORD
