Metadata-Version: 2.4
Name: ossdbs
Version: 0.5.3
Summary: OSS-DBS v2: faster and modular open-source code for deep brain stimulation
Author-email: Julius Zimmermann <julius.zimmermann@uni-rostock.de>, Jan Philipp Payonk <jan.payonk@uni-rostock.de>, Tom Reincke <tom.reincke@uni-rostock.de>, Johannes Reding <johannes.reding@uni-rostock.de>, Konstantin Butenko <kbutenko@bwh.harvard.edu>, Shruthi Chakravarthy <shruthi.chakravarthy@uni-rostock.de>
License:                     GNU GENERAL PUBLIC LICENSE
Project-URL: homepage, https://oss-dbsv2.readthedocs.io/en/latest/
Project-URL: repository, https://github.com/SFB-ELAINE/oss-dbsv2
Classifier: Development Status :: 3 - Alpha
Classifier: Programming Language :: Python :: 3
Classifier: Programming Language :: Python :: 3.10
Classifier: Programming Language :: Python :: 3.11
Classifier: Programming Language :: Python :: 3.12
Classifier: Programming Language :: Python :: 3.13
Classifier: License :: OSI Approved :: GNU General Public License v3 or later (GPLv3+)
Classifier: Operating System :: OS Independent
Requires-Python: >=3.10
License-File: LICENSE
Requires-Dist: h5py==3.14.0
Requires-Dist: ngsolve==6.2.2501
Requires-Dist: nibabel==5.2.1
Requires-Dist: pandas
Requires-Dist: scipy
Requires-Dist: matplotlib
Requires-Dist: neuron==8.2.7; platform_system == "Linux"
Requires-Dist: neuron==8.2.7; platform_system == "Darwin"
Requires-Dist: numpy<2; platform_system == "Windows"
Requires-Dist: dipy>=1.8.0
Provides-Extra: test
Requires-Dist: pytest; extra == "test"
Requires-Dist: pytest-cov; extra == "test"
Requires-Dist: pytest-mock; extra == "test"
Provides-Extra: dev
Requires-Dist: ruff; extra == "dev"
Requires-Dist: pre-commit; extra == "dev"
Provides-Extra: doc
Requires-Dist: sphinx==6.1.3; extra == "doc"
Requires-Dist: sphinx-rtd-theme==1.2.0; extra == "doc"
Provides-Extra: all
Requires-Dist: ossdbs[dev,doc,test]; extra == "all"
Dynamic: license-file
